les_iterables/__init__.py
les_iterables/augmenting.py
les_iterables/combining.py
les_iterables/functions.py
les_iterables/generating.py
les_iterables/grouping.py
les_iterables/parsing.py
les_iterables/searching.py
les_iterables/selecting.py
les_iterables/sentinels.py
les_iterables/sequences.py
les_iterables/version.py
les_iterables-1.15.0.dist-info/LICENSE.txt
les_iterables-1.15.0.dist-info/METADATA
les_iterables-1.15.0.dist-info/WHEEL
les_iterables-1.15.0.dist-info/top_level.txt
les_iterables-1.15.0.dist-info/zip-safe
les_iterables-1.15.0.dist-info/RECORD
