Metadata-Version: 2.1
Name: les_iterables
Version: 1.15.0
Summary: Iterable processing functions
Home-page: https://github.com/sixty-north/les_iterables
Author: Sixty North AS
Author-email: systems+les_iterables@sixty-north.com
License: MIT License
Keywords: iterators iterables
Classifier: Development Status :: 5 - Production/Stable
Classifier: Intended Audience :: Developers
Classifier: Topic :: Software Development :: Libraries :: Python Modules
Classifier: License :: OSI Approved :: MIT License
Classifier: Programming Language :: Python :: 3 :: Only
Classifier: Programming Language :: Python :: 3.10
Classifier: Programming Language :: Python :: 3.11
Classifier: Programming Language :: Python :: 3.12
Classifier: Programming Language :: Python :: 3.13
License-File: LICENSE.txt
Requires-Dist: more-itertools
Provides-Extra: dev
Requires-Dist: bumpversion ; extra == 'dev'
Provides-Extra: doc
Requires-Dist: sphinx ; extra == 'doc'
Requires-Dist: sphinx-rtd-theme ; extra == 'doc'
Requires-Dist: better-apidoc ; extra == 'doc'
Provides-Extra: test
Requires-Dist: pytest ; extra == 'test'
Requires-Dist: coverage ; extra == 'test'
Requires-Dist: pytest-cov ; extra == 'test'
Requires-Dist: hypothesis ; extra == 'test'
Requires-Dist: tox ; extra == 'test'
